treetagger_xml/__init__.py
treetagger_xml/constants.py
treetagger_xml/process.py
treetagger_xml/treetagger2opus.py
treetagger_xml/txt.py
treetagger_xml/utils.py
treetagger_xml/xml.py
treetagger_xml-0.1.9.dist-info/LICENSE
treetagger_xml-0.1.9.dist-info/METADATA
treetagger_xml-0.1.9.dist-info/WHEEL
treetagger_xml-0.1.9.dist-info/top_level.txt
treetagger_xml-0.1.9.dist-info/RECORD
