Metadata-Version: 2.1
Name: treetagger-xml
Version: 0.1.9
Summary: Reads .xml/.txt-files and parses these with TreeTagger
Home-page: https://github.com/time-in-translation/treetagger-xml
Author: Martijn van der Klis
Author-email: m.h.vanderklis@uu.nl
License: MIT
Platform: UNKNOWN
Classifier: Topic :: Text Processing :: Linguistic
Classifier: Programming Language :: Python :: 3
Classifier: License :: OSI Approved :: MIT License
Classifier: Operating System :: POSIX :: Linux
Requires-Dist: lxml
Requires-Dist: six
Requires-Dist: treetaggerwrapper
